pynite_plotly/__init__.py
pynite_plotly/py.typed
pynite_plotly/rendering.py
pynite_plotly-0.4.1.dist-info/WHEEL
pynite_plotly-0.4.1.dist-info/METADATA
pynite_plotly-0.4.1.dist-info/RECORD
