Metadata-Version: 2.4
Name: pynite-plotly
Version: 0.4.1
Summary: A 3rd party visualization module for PyNiteFEA using plotly
Author-email: Connor Ferster <connor@structuralpython.com>
Requires-Python: >=3.10
Requires-Dist: ipykernel>=6.29.5
Requires-Dist: plotly-3d-primitives>=0.4.0
